odoo/addons/shopinvader_product_description/README.rst
odoo/addons/shopinvader_product_description/__init__.py
odoo/addons/shopinvader_product_description/__manifest__.py
odoo/addons/shopinvader_product_description/i18n/shopinvader_product_description.pot
odoo/addons/shopinvader_product_description/models/__init__.py
odoo/addons/shopinvader_product_description/models/product_category.py
odoo/addons/shopinvader_product_description/readme/CONTRIBUTORS.rst
odoo/addons/shopinvader_product_description/readme/DESCRIPTION.rst
odoo/addons/shopinvader_product_description/schemas/__init__.py
odoo/addons/shopinvader_product_description/schemas/category.py
odoo/addons/shopinvader_product_description/schemas/product.py
odoo/addons/shopinvader_product_description/static/description/index.html
odoo/addons/shopinvader_product_description/views/product_category.xml
odoo_addon_shopinvader_product_description-16.0.1.0.0.3.dist-info/METADATA
odoo_addon_shopinvader_product_description-16.0.1.0.0.3.dist-info/WHEEL
odoo_addon_shopinvader_product_description-16.0.1.0.0.3.dist-info/top_level.txt
odoo_addon_shopinvader_product_description-16.0.1.0.0.3.dist-info/RECORD
